introspection/__init__.py
introspection/_utils.py
introspection/argument_bundle.py
introspection/bound_arguments.py
introspection/call_frame.py
introspection/call_stack.py
introspection/classes.py
introspection/dunder.py
introspection/dundermethods.py
introspection/errors.py
introspection/exceptions.py
introspection/hazmat.py
introspection/mark.py
introspection/misc.py
introspection/misc2.py
introspection/parameter.py
introspection/signature_.py
introspection/signature_db.py
introspection/types.py
introspection/typing/__init__.py
introspection/typing/_compat.py
introspection/typing/_utils.py
introspection/typing/forward_ref.py
introspection/typing/i_hate_circular_imports.py
introspection/typing/instance_check.py
introspection/typing/introspection.py
introspection/typing/misc.py
introspection/typing/misc2.py
introspection/typing/subtype_check.py
introspection/typing/type_compat.py
introspection/typing/type_info.py
introspection-1.12.1.dist-info/licenses/LICENSE
introspection-1.12.1.dist-info/WHEEL
introspection-1.12.1.dist-info/METADATA
introspection-1.12.1.dist-info/RECORD
