Metadata-Version: 2.4
Name: introspection
Version: 1.12.1
Summary: New and improved introspection functions
Author: Paul Pinterits
Requires-Python: >=3.10
License-File: LICENSE
Requires-Dist: ordered-set
Requires-Dist: sentinel
Requires-Dist: typing-extensions
Requires-Dist: sphinx ; extra == "doc"
Requires-Dist: pytest ; extra == "test"
Requires-Dist: pytest-raisin ; extra == "test"
Requires-Dist: tox ; extra == "test"
Requires-Dist: coverage ; extra == "test"
Project-URL: documentation, https://Aran-Fey.github.io/introspection/docs/build/index.html
Project-URL: repository, https://github.com/Aran-Fey/introspection
Provides-Extra: doc
Provides-Extra: test
